CHANGES.rst
MANIFEST.in
README.rst
setup.cfg
setup.py
src/Products/__init__.py
src/Products.SimpleAttachment.egg-info/PKG-INFO
src/Products.SimpleAttachment.egg-info/SOURCES.txt
src/Products.SimpleAttachment.egg-info/dependency_links.txt
src/Products.SimpleAttachment.egg-info/namespace_packages.txt
src/Products.SimpleAttachment.egg-info/not-zip-safe
src/Products.SimpleAttachment.egg-info/requires.txt
src/Products.SimpleAttachment.egg-info/top_level.txt
src/Products/SimpleAttachment/__init__.py
src/Products/SimpleAttachment/browser.py
src/Products/SimpleAttachment/config.py
src/Products/SimpleAttachment/configure.zcml
src/Products/SimpleAttachment/extenders.py
src/Products/SimpleAttachment/filename_normalizer.py
src/Products/SimpleAttachment/interfaces.py
src/Products/SimpleAttachment/rebuild_i18n.sh
src/Products/SimpleAttachment/setuphandlers.py
src/Products/SimpleAttachment/content/__init__.py
src/Products/SimpleAttachment/content/file.py
src/Products/SimpleAttachment/content/image.py
src/Products/SimpleAttachment/locales/simpleattachment.pot
src/Products/SimpleAttachment/locales/de/LC_MESSAGES/simpleattachment.mo
src/Products/SimpleAttachment/locales/de/LC_MESSAGES/simpleattachment.po
src/Products/SimpleAttachment/locales/en/LC_MESSAGES/simpleattachment.mo
src/Products/SimpleAttachment/locales/en/LC_MESSAGES/simpleattachment.po
src/Products/SimpleAttachment/locales/es/LC_MESSAGES/simpleattachment.mo
src/Products/SimpleAttachment/locales/es/LC_MESSAGES/simpleattachment.po
src/Products/SimpleAttachment/locales/it/LC_MESSAGES/simpleattachment.mo
src/Products/SimpleAttachment/locales/it/LC_MESSAGES/simpleattachment.po
src/Products/SimpleAttachment/locales/nl/LC_MESSAGES/simpleattachment.mo
src/Products/SimpleAttachment/locales/nl/LC_MESSAGES/simpleattachment.po
src/Products/SimpleAttachment/migration/__init__.py
src/Products/SimpleAttachment/migration/configure.zcml
src/Products/SimpleAttachment/migration/migration.pt
src/Products/SimpleAttachment/migration/migrations.py
src/Products/SimpleAttachment/profiles/default/import_steps.xml
src/Products/SimpleAttachment/profiles/default/metadata.xml
src/Products/SimpleAttachment/profiles/default/propertiestool.xml
src/Products/SimpleAttachment/profiles/default/simpleattachment_various.txt
src/Products/SimpleAttachment/profiles/default/skins.xml
