Metadata-Version: 1.1
Name: Products.SimpleAttachment
Version: 5.0.0
Summary: Simple Attachments for Plone
Home-page: https://github.com/collective/Products.SimpleAttachment
Author: Martin Aspeli
Author-email: optilude@gmail.com
License: GPL
Keywords: Plone attachments RichDocument
Platform: UNKNOWN
Classifier: Framework :: Plone
Classifier: Framework :: Plone :: 4.3
Classifier: Framework :: Zope2
Classifier: Programming Language :: Python
Classifier: Programming Language :: Python :: 2.7
